README.md
setup.py
NVR.egg-info/PKG-INFO
NVR.egg-info/SOURCES.txt
NVR.egg-info/dependency_links.txt
NVR.egg-info/requires.txt
NVR.egg-info/top_level.txt
nvr/NVR.py
nvr/__init__.py