Metadata-Version: 1.0
Name: NVR
Version: 0.0.2
Summary: python implementation of gene feature selection used in Welch et al.,2016
Home-page: https://github.com/KenLauLab/NVR
Author: Bob Chen
Author-email: bob.chen@vanderbilt.edu
License: UNKNOWN
Platform: UNKNOWN
